academic/cli.py
academic/generate_markdown.py
academic/import_bibtex.py
academic/import_notebook.py
academic/jupyter_whitespace_remover.py
academic/publication_type.py
academic/templates/publication.md
academic/utils.py
academic-0.11.1.dist-info/LICENSE.md
academic-0.11.1.dist-info/METADATA
academic-0.11.1.dist-info/WHEEL
academic-0.11.1.dist-info/entry_points.txt
academic-0.11.1.dist-info/RECORD
