Metadata-Version: 2.1
Name: academic
Version: 0.11.1
Summary: Import Bibtex publications and Jupyter Notebook blog posts into your Markdown-formatted website or book.
Home-page: https://wowchemy.com
License: MIT
Keywords: wowchemy,bibtex,markdown,latex,publication,reference
Author: George Cushen
Requires-Python: >=3.11.5
Classifier: License :: OSI Approved :: MIT License
Classifier: Programming Language :: Python :: 3
Classifier: Programming Language :: Python :: 3.12
Requires-Dist: bibtexparser (>=1.4,<1.5)
Requires-Dist: nbconvert (>=7.10.0,<8.0.0)
Requires-Dist: pyyaml (>=6.0.1,<7.0.0)
Requires-Dist: ruamel.yaml (>=0.17,<0.18)
Project-URL: Repository, https://github.com/wowchemy/bibtex-to-markdown
